health_check_utils/__init__.py
health_check_utils/health.py
health_check_utils-0.1.0.dist-info/METADATA
health_check_utils-0.1.0.dist-info/WHEEL
health_check_utils-0.1.0.dist-info/RECORD
